habraparse/__init__.py
habraparse/habr/__init__.py
habraparse/habr/topic.py
habraparse/parser/__init__.py
habraparse/parser/chrome/HabrParser.py
habraparse/parser/chrome/__init__.py
habraparse/parser/classic/HabrParser.py
habraparse/parser/classic/__init__.py
habraparse/renderer/__init__.py
habraparse/renderer/chrome/HabrArticleRenderer.py
habraparse/renderer/chrome/__init__.py
habraparse/renderer/pdfkit/HabrArticleRenderer.py
habraparse/renderer/pdfkit/__init__.py
habraparse/renderer/weasyprint/HabrArticleRenderer.py
habraparse/renderer/weasyprint/__init__.py
habraparse-1.0.0.dist-info/LICENSE.GPL2
habraparse-1.0.0.dist-info/METADATA
habraparse-1.0.0.dist-info/WHEEL
habraparse-1.0.0.dist-info/top_level.txt
habraparse-1.0.0.dist-info/RECORD
