Metadata-Version: 2.1
Name: habraparse
Version: 1.0.0
Summary: Парсер Habr
Author-email: icoz <icoz.vt@gmail.com>, vit1251 <vit1251@gmail.com>
Maintainer-email: ST LEON <leonst998@gmail.com>, vit1251 <vit1251@gmail.com>
Project-URL: repository, https://github.com/vit1251/habraparse
Requires-Python: >=3.8
License-File: LICENSE.GPL2
Requires-Dist: weasyprint
Requires-Dist: selenium
Requires-Dist: requests
Requires-Dist: lxml
